{
  "Sale of apartments": "Sale of apartments",
  "Houses for sale": "Houses for sale",
  "Apartments for rent": "Apartments for rent",
  "Updates": "Updates",
  "Details": "Details",
  "Select the type of real estate": "Select the type of real estate",
  "Sign up": "Sign up",
  "Login": "Login",
  "Post": "Post",
  "Sign out": "Sign out",
  "Residential land": "Residential land",
  "Address": "Address",
  "Area": "Area",
  "Contact Phone": "Contact Phone",
  "Open account": "Open account",
  "Change password": "Change password",
  "Agree": "Agree",
  "Email (to retrieve password)": "Email (to retrieve password)",
  "Price": "Price (VND)",
  "Effect": "Effect",
  "Picture": "Picture",
  "Avatar": "Avatar",
  "Name": "Name",
  "Cancel": "Cancel",
  "Hotel": "Hotel",
  "Highlight": "Highlight",
  "Retrieve password": "Retrieve password",
  "Contact help": "Contact help",
  "Type of real estate": "Type of real estate",
  "Password": "Password",
  "Square meters": "Square meters",
  "Contact Person": "Contact Person",
  "Accommodation": "Accommodation",
  "Forgot password": "Forgot password",
  "Chinese": "Chinese",
  "Posted history": "Posted history",
  "Pinned": "Pinned",
  "Maximum of 8 characters": "Maximum of 8 characters",
  "From": "From",
  "To": "To",
  "Personal information": "Personal information",
  "Rent": "Rent",
  "Personal page": "Personal page",
  "Wallet": "Wallet",
  "Villa": "Villa",
  "Please input address": "Please input address",
  "Please enter detailed information": "Please enter detailed information",
  "Confirm password": "Confirm password"
}